oneNeuron/__init__.py
oneNeuron/perceptron.py
Perceptron_package_kapoorparas09-0.0.1.dist-info/LICENSE
Perceptron_package_kapoorparas09-0.0.1.dist-info/METADATA
Perceptron_package_kapoorparas09-0.0.1.dist-info/WHEEL
Perceptron_package_kapoorparas09-0.0.1.dist-info/top_level.txt
Perceptron_package_kapoorparas09-0.0.1.dist-info/RECORD
