Metadata-Version: 2.1
Name: Perceptron-package-kapoorparas09
Version: 0.0.1
Summary: Perceptron implementation as a package
Home-page: https://github.com/kapoorparas09/Perceptron_package
Author: kapoorparas09
Author-email: kapoorparas0001@gmail.com
Project-URL: Bug Tracker, https://github.com/kapoorparas09/Perceptron_package/issues
Classifier: Programming Language :: Python :: 3
Classifier: License :: OSI Approved :: MIT License
Classifier: Operating System :: OS Independent
Requires-Python: >=3.9
License-File: LICENSE
Requires-Dist: numpy
Requires-Dist: tqdm
